fastapi_rest_toolkit/__init__.py
fastapi_rest_toolkit/contextvar.py
fastapi_rest_toolkit/filters.py
fastapi_rest_toolkit/permissions.py
fastapi_rest_toolkit/request.py
fastapi_rest_toolkit/router.py
fastapi_rest_toolkit/service.py
fastapi_rest_toolkit/throttle.py
fastapi_rest_toolkit/utils.py
fastapi_rest_toolkit/viewset.py
fastapi_rest_toolkit-0.0.3.dist-info/METADATA
fastapi_rest_toolkit-0.0.3.dist-info/WHEEL
fastapi_rest_toolkit-0.0.3.dist-info/licenses/LICENSE
fastapi_rest_toolkit-0.0.3.dist-info/RECORD
