Metadata-Version: 2.4
Name: fastapi-rest-toolkit
Version: 0.0.3
Summary: 类DRF风格的FastAPI工具包
Project-URL: Homepage, https://github.com/pppigrui/fastapi-rest-toolkit
Project-URL: Documentation, https://github.com/pppigrui/fastapi-rest-toolkit#readme
Project-URL: Repository, https://github.com/pppigrui/fastapi-rest-toolkit
Project-URL: Bug Tracker, https://github.com/pppigrui/fastapi-rest-toolkit/issues
Author-email: xiaorui <pppigrui@gmail.com>
License: MIT
License-File: LICENSE
Keywords: api,drf,fastapi,rest,toolkit
Classifier: Development Status :: 3 - Alpha
Classifier: Framework :: FastAPI
Classifier: Intended Audience :: Developers
Classifier: License :: OSI Approved :: MIT License
Classifier: Programming Language :: Python :: 3
Classifier: Programming Language :: Python :: 3.12
Classifier: Topic :: Software Development :: Libraries :: Python Modules
Requires-Python: >=3.12
Requires-Dist: fastapi>=0.128.0
Requires-Dist: pydantic>=2.12.0
Requires-Dist: redis>=7.1.0
Requires-Dist: sqlalchemy-crud-plus>=1.13.0
Requires-Dist: sqlalchemy>=2.0.46
Provides-Extra: all
Requires-Dist: redis>=5.0.0; extra == 'all'
Provides-Extra: redis
Requires-Dist: redis>=5.0.0; extra == 'redis'
